pie/__init__.py
pie/json_loader.py
pie/yaml_loader.py
painless_import_extension-0.2.2.dist-info/LICENSE
painless_import_extension-0.2.2.dist-info/METADATA
painless_import_extension-0.2.2.dist-info/WHEEL
painless_import_extension-0.2.2.dist-info/entry_points.txt
painless_import_extension-0.2.2.dist-info/top_level.txt
painless_import_extension-0.2.2.dist-info/RECORD
