Metadata-Version: 2.1
Name: painless-import-extension
Version: 0.2.2
Summary: UNKNOWN
Home-page: https://github.com/thautwarm/painless-import-extension
Author: thautwarm
Author-email: twshere@outlook.com
License: mit
Platform: any
Classifier: Programming Language :: Python :: 3.4
Classifier: Programming Language :: Python :: 3.5
Classifier: Programming Language :: Python :: 3.6
Classifier: Programming Language :: Python :: 3.7
Classifier: Programming Language :: Python :: 3.8
Classifier: Programming Language :: Python :: Implementation :: CPython
Requires-Python: >=3
